Workbook

Sheet Modules & Stack
A1: AI-SoulMatch — What costs money (current stack)
A2: Yellow cells anywhere in this workbook = your inputs. Green = calculated.
A4: Module / Page | B4: What it does | C4: Tool / API used today | D4: Costs money? | E4: Cost driver
A5: Ingest (pages_/2_Ingest.py) | B5: Parse WhatsApp chat export, extract candidate profiles | C5: LLM via soulmatch/extraction/llm.py — Gemini (gemini-flash-latest) / Anthropic / local / mock | D5: YES (LLM) | E5: Tokens per profile extracted
A6: Profiles (3_Profiles.py) | B6: Re-extract / enrich a single profile from pasted text or biodata | C6: Same LLM layer | D6: YES (LLM) | E6: Tokens per extraction
A7: Matching (4_Matching.py) | B7: Rule-based candidate filtering + AI recommendation / explanation | C7: Rules: soulmatch/matching/rules.py (local, free). Explanations: LLM (recommendation.py) | D7: PARTLY | E7: Only the AI-explanation calls
A8: NL Search (8_Search.py) | B8: Natural-language search over profiles | C8: LLM (soulmatch/search.py) | D8: YES (LLM) | E8: Tokens per query
A9: Astrology (5_Astrology.py) | B9: Koota (ashtakoota) score, dosha checks, geo lookup | C9: pyswisseph + own koota/dosha code — 100% local | D9: NO | E9: CPU only
A10: Dashboard / Tasks / Users | B10: CRM views, follow-ups, auth | C10: Streamlit + SQLite | D10: NO | E10: —
A11: Database | B11: All app data | C11: SQLite (file on disk) | D11: NO | E11: Disk only (upgrade to Postgres later)
A12: Hosting | B12: Runs the Streamlit app | C12: Currently local machine; plan: small VPS | D12: YES (fixed) | E12: Flat monthly VPS fee
A13: Payments | B13: Subscriptions (planned) | C13: Razorpay / Cashfree + UPI Autopay (planned) | D13: YES (variable) | E13: ~2% of every payment
A14: Ephemeris / geo data | B14: Planet positions, city coords | C14: Swiss Ephemeris files + offline geo table | D14: NO | E14: One-time bundled data
A16: Key point: only 4 code paths hit a paid API, and every one of them is meterable per user. Astrology — the flagship feature — is free compute.

Sheet Assumptions
A1: Global assumptions (edit yellow cells)
A3: USD → INR exchange rate | B3: 86 | C3: Update as needed
A4: LLM input price ($ per 1M tokens) | B4: 0.3 | C4: Gemini 2.5 Flash paid tier (default model)
A5: LLM output price ($ per 1M tokens) | B5: 2.5 | C5: Gemini 2.5 Flash
A6: Payment gateway fee (% of revenue) | B6: 0.02 | C6: Razorpay standard ~2% + GST on fee
A7: GST on gateway fee (18% of the fee) | B7: 0.18 | C7: Effective gateway cost ≈ 2.36%
A8: Free→Paid users ratio (free users per paid) | B8: 5 | C8: Every paid user 'carries' this many free users' API cost
A10: Fixed monthly costs (₹)
A11: VPS hosting (e.g. Hetzner CX22 / DO 2GB — runs Streamlit + SQLite fine to ~1–2k users) | B11: 700
A12: Domain (₹1,200/yr amortized) | B12: 100
A13: Object storage + offsite DB backups (photos/PDFs) | B13: 150
A14: Transactional email (login/receipts — free tier at first) | B14: 0
A15: Error monitoring / uptime (free tiers) | B15: 0
A16: Misc / buffer | B16: 200
A17: TOTAL FIXED / MONTH | B17: =SUM(B11:B16)

Sheet Cost per AI action
A1: Cost per AI action (Gemini 2.5 Flash prices from Assumptions)
A3: AI action (module) | B3: Input tokens | C3: Output tokens | D3: Cost $ | E3: Cost ₹
A4: WhatsApp profile extraction (Ingest) | B4: 3000 | C4: 1000 | D4: =(B4*Assumptions!$B$4+C4*Assumptions!$B$5)/1000000 | E4: =D4*Assumptions!$B$3
A5: PDF biodata parse (Ingest/Profiles) | B5: 5000 | C5: 1200 | D5: =(B5*Assumptions!$B$4+C5*Assumptions!$B$5)/1000000 | E5: =D5*Assumptions!$B$3
A6: Image OCR + extract (Ingest) | B6: 2500 | C6: 1000 | D6: =(B6*Assumptions!$B$4+C6*Assumptions!$B$5)/1000000 | E6: =D6*Assumptions!$B$3
A7: Match explanation / compare (Matching) | B7: 4000 | C7: 1500 | D7: =(B7*Assumptions!$B$4+C7*Assumptions!$B$5)/1000000 | E7: =D7*Assumptions!$B$3
A8: NL search query (Search) | B8: 2000 | C8: 500 | D8: =(B8*Assumptions!$B$4+C8*Assumptions!$B$5)/1000000 | E8: =D8*Assumptions!$B$3
A9: BLENDED AVERAGE per action | E9: =AVERAGE(E4:E8)
A11: Free for you (₹0): koota/dosha scores (pyswisseph), rule-based match filters, dashboards, tasks.

Sheet Tier unit economics
A1: Per-subscriber monthly P&L by tier
B3: Free | C3: Plus | D3: Pro
A4: Price / month (₹) | B4: 0 | C4: 149 | D4: 399
A5: AI-action quota / month | B5: 15 | C5: 150 | D5: 500
A6: Expected actual usage (% of quota) | B6: 0.6 | C6: 0.45 | D6: 0.35
A7: AI actions actually used | B7: =B5*B6 | C7: =C5*C6 | D7: =D5*D6
A8: API cost (₹) | B8: =B7*'Cost per AI action'!$E$9 | C8: =C7*'Cost per AI action'!$E$9 | D8: =D7*'Cost per AI action'!$E$9
A9: Gateway fee incl. GST (₹) | B9: =B4*Assumptions!$B$6*(1+Assumptions!$B$7) | C9: =C4*Assumptions!$B$6*(1+Assumptions!$B$7) | D9: =D4*Assumptions!$B$6*(1+Assumptions!$B$7)
A10: Contribution margin / user / month (₹) | B10: =B4-B8-B9 | C10: =C4-C8-C9 | D10: =D4-D8-D9
A11: Margin % | B11: n/a | C11: =C10/C4 | D11: =D10/D4
A13: Note: 'Expected usage %' reflects that most subscribers never exhaust quotas. Worst case (100% usage) is still profitable — set the % to 100 to check.

Sheet Break-even
A1: Break-even: paid subscribers needed to cover fixed costs + free users
A3: Fixed costs / month (from Assumptions) | B3: =Assumptions!$B$17
A4: Free-user API cost each (₹/mo) | B4: ='Tier unit economics'!B8
A5: Free users carried per paid user | B5: =Assumptions!$B$8
A7: Scenario mix | B7: % Plus | C7: % Pro | D7: Blended margin/paid user ₹ | E7: Paid subs to break even
A8: Conservative (mostly Plus) | B8: 0.9 | C8: 0.1 | D8: =B8*'Tier unit economics'!C10+C8*'Tier unit economics'!D10-$B$5*$B$4 | E8: =ROUNDUP($B$3/D8,0)
A9: Balanced | B9: 0.75 | C9: 0.25 | D9: =B9*'Tier unit economics'!C10+C9*'Tier unit economics'!D10-$B$5*$B$4 | E9: =ROUNDUP($B$3/D9,0)
A10: Pro-heavy | B10: 0.5 | C10: 0.5 | D10: =B10*'Tier unit economics'!C10+C10*'Tier unit economics'!D10-$B$5*$B$4 | E10: =ROUNDUP($B$3/D10,0)
A12: Monthly profit at N paid subscribers (Balanced mix)
A13: Paid subscribers | B13: Revenue ₹ | C13: All costs ₹ | D13: Profit ₹
A14: 10 | B14: =A14*(0.75*'Tier unit economics'!C4+0.25*'Tier unit economics'!D4) | C14: =$B$3 + A14*(0.75*('Tier unit economics'!C8+'Tier unit economics'!C9)+0.25*('Tier unit economics'!D8+'Tier unit economics'!D9)) + A14*$B$5*$B$4 | D14: =B14-C14
A15: 25 | B15: =A15*(0.75*'Tier unit economics'!C4+0.25*'Tier unit economics'!D4) | C15: =$B$3 + A15*(0.75*('Tier unit economics'!C8+'Tier unit economics'!C9)+0.25*('Tier unit economics'!D8+'Tier unit economics'!D9)) + A15*$B$5*$B$4 | D15: =B15-C15
A16: 50 | B16: =A16*(0.75*'Tier unit economics'!C4+0.25*'Tier unit economics'!D4) | C16: =$B$3 + A16*(0.75*('Tier unit economics'!C8+'Tier unit economics'!C9)+0.25*('Tier unit economics'!D8+'Tier unit economics'!D9)) + A16*$B$5*$B$4 | D16: =B16-C16
A17: 100 | B17: =A17*(0.75*'Tier unit economics'!C4+0.25*'Tier unit economics'!D4) | C17: =$B$3 + A17*(0.75*('Tier unit economics'!C8+'Tier unit economics'!C9)+0.25*('Tier unit economics'!D8+'Tier unit economics'!D9)) + A17*$B$5*$B$4 | D17: =B17-C17
A18: 250 | B18: =A18*(0.75*'Tier unit economics'!C4+0.25*'Tier unit economics'!D4) | C18: =$B$3 + A18*(0.75*('Tier unit economics'!C8+'Tier unit economics'!C9)+0.25*('Tier unit economics'!D8+'Tier unit economics'!D9)) + A18*$B$5*$B$4 | D18: =B18-C18
A19: 500 | B19: =A19*(0.75*'Tier unit economics'!C4+0.25*'Tier unit economics'!D4) | C19: =$B$3 + A19*(0.75*('Tier unit economics'!C8+'Tier unit economics'!C9)+0.25*('Tier unit economics'!D8+'Tier unit economics'!D9)) + A19*$B$5*$B$4 | D19: =B19-C19
A20: 1000 | B20: =A20*(0.75*'Tier unit economics'!C4+0.25*'Tier unit economics'!D4) | C20: =$B$3 + A20*(0.75*('Tier unit economics'!C8+'Tier unit economics'!C9)+0.25*('Tier unit economics'!D8+'Tier unit economics'!D9)) + A20*$B$5*$B$4 | D20: =B20-C20
A22: All costs = fixed + paid users' API & gateway + free users' API (5 free per paid by default).
